[
  {
    "id": 2,
    "name": "\u0642\u0646\u0627\u0629 \u0627\u0644\u0633\u0639\u0648\u062f\u064a\u0629 \u2013 \u0627\u0644\u0628\u062b \u0627\u0644\u0645\u0628\u0627\u0634\u0631",
    "logo": "",
    "stream": "https://live.kwikmotion.com/ksa1live/ksa1.smil/playlist_dvr.m3u8?hdnts=exp=1776680971~acl=/ksa1live/ksa1.smil/*~hmac=892fbd8e65320258d6eae38bc3aa646caec0b3cd22f327b40757dadf4f297bc8"
  },
  {
    "id": 1,
    "name": "\u0642\u0646\u0627\u0629 SBC \u2013 \u0627\u0644\u0628\u062b \u0627\u0644\u0645\u0628\u0627\u0634\u0631",
    "logo": "",
    "stream": "https://live.kwikmotion.com/sbclive/sbc.smil/playlist_dvr.m3u8?hdnts=exp=1776680972~acl=/sbclive/sbc.smil/*~hmac=541d7650f83157d0c6fc4e48de6df697a33e679b931c53aa218b8670b48fcae2"
  },
  {
    "id": 4,
    "name": "\u0642\u0646\u0627\u0629 \u0627\u0644\u0625\u062e\u0628\u0627\u0631\u064a\u0629 \u2013 \u0627\u0644\u0628\u062b \u0627\u0644\u0645\u0628\u0627\u0634\u0631",
    "logo": "",
    "stream": "https://live.kwikmotion.com/ikhbariyalive/ikhbariya.smil/playlist_dvr.m3u8?hdnts=exp=1776680973~acl=/ikhbariyalive/ikhbariya.smil/*~hmac=ef65f902a7fc26d534fd3ade088323f9e2a3c9feb1be88f5de229511fa123b70"
  },
  {
    "id": 17,
    "name": "\u0627\u0644\u0633\u0639\u0648\u062f\u064a\u0629 \u0627\u0644\u0622\u0646",
    "logo": "",
    "stream": "https://live.kwikmotion.com/ksasports4live/ksasports4.smil/playlist_dvr.m3u8?hdnts=exp=1776680975~acl=/ksasports4live/ksasports4.smil/*~hmac=4d133677a4c56bd859dab84d68599cd9c9df9daffd96baf99069d3493b62498a"
  },
  {
    "id": 3,
    "name": "\u0642\u0646\u0627\u0629 \u0630\u0643\u0631\u064a\u0627\u062a \u2013 \u0627\u0644\u0628\u062b \u0627\u0644\u0645\u0628\u0627\u0634\u0631",
    "logo": "",
    "stream": "https://live.kwikmotion.com/zikrayatlive/zikrayat.smil/playlist_dvr.m3u8?hdnts=exp=1776680976~acl=/zikrayatlive/zikrayat.smil/*~hmac=4928a92b97e39b7cb3488e306efa27d36e61a176a419ad0a9195e041dbc24f88"
  },
  {
    "id": 7,
    "name": "\u0642\u0646\u0627\u0629 \u0627\u0644\u0642\u0631\u0622\u0646 \u0627\u0644\u0643\u0631\u064a\u0645 \u2013 \u0627\u0644\u0628\u062b \u0627\u0644\u0645\u0628\u0627\u0634\u0631",
    "logo": "",
    "stream": "https://live.kwikmotion.com/ksaquranlive/ksaquran.smil/playlist_dvr.m3u8?hdnts=exp=1776680976~acl=/ksaquranlive/ksaquran.smil/*~hmac=45982a98b524a477101af4064d1edf0f09f24b108771a43d425e1c2b6e3ea895"
  },
  {
    "id": 6,
    "name": "\u0642\u0646\u0627\u0629 \u0627\u0644\u0633\u0646\u0629 \u0627\u0644\u0646\u0628\u0648\u064a\u0629 \u2013 \u0627\u0644\u0628\u062b \u0627\u0644\u0645\u0628\u0627\u0634\u0631",
    "logo": "",
    "stream": "https://live.kwikmotion.com/ksasunnalive/ksasunna.smil/playlist_dvr.m3u8?hdnts=exp=1776680978~acl=/ksasunnalive/ksasunna.smil/*~hmac=b4077635a4309e07329e4dd6161a7caa7f000ace640cdc6bed65eb428ded7dc3"
  },
  {
    "id": 9,
    "name": "\u0642\u0646\u0627\u0629 \u0627\u0644\u0631\u064a\u0627\u0636\u064a\u0629 1",
    "logo": "",
    "stream": "https://live.kwikmotion.com/ksasports1live/ksasports1.smil/playlist_dvr.m3u8?hdnts=exp=1776680980~acl=/ksasports1live/ksasports1.smil/*~hmac=77ec19eb465ca48f492ae6c9696312c79194f8941c0ee7ea0b9e96d1f0bfdc08"
  },
  {
    "id": 10,
    "name": "\u0642\u0646\u0627\u0629 \u0627\u0644\u0631\u064a\u0627\u0636\u064a\u0629 2",
    "logo": "",
    "stream": "https://live.kwikmotion.com/ksasports2live/ksasports2.smil/playlist_dvr.m3u8?hdnts=exp=1776680981~acl=/ksasports2live/ksasports2.smil/*~hmac=15b59f730c9f5de5b5a7d872ba7dcdd558670722fb880951937c4562180e49f7"
  },
  {
    "id": 16,
    "name": "\u0642\u0646\u0627\u0629 \u0627\u0644\u0631\u064a\u0627\u0636\u064a\u0629 3",
    "logo": "",
    "stream": "https://live.kwikmotion.com/ksasports3live/ksasports3.smil/playlist_dvr.m3u8?hdnts=exp=1776680979~acl=/ksasports3live/ksasports3.smil/*~hmac=a2034c6fbc90f05c4e69cf757fb23480b10a7d50af046e1371ffe5192deb1509"
  },
  {
    "id": 12,
    "name": "\u0625\u0630\u0627\u0639\u0629 \u0627\u0644\u0631\u064a\u0627\u0636",
    "logo": "",
    "stream": "https://live.kwikmotion.com/ksariyadhradiolive/ksariyadhradiovision/playlist_dvr.m3u8?hdnts=exp=1776680983~acl=/ksariyadhradiolive/ksariyadhradiovision/*~hmac=e54a7b42a812512c9aee23f57774e6dde20ee6e9dddfc65195027e98ac9f101f"
  },
  {
    "id": 15,
    "name": "\u0625\u0630\u0627\u0639\u0629 \u062c\u062f\u0629",
    "logo": "",
    "stream": "https://live.kwikmotion.com/ksajeddahradiolive/ksajeddahradiovision/playlist_dvr.m3u8?hdnts=exp=1776680985~acl=/ksajeddahradiolive/ksajeddahradiovision/*~hmac=bbcb01144dd17718a099f94c827e80d547e329e5acbe69559cf2797a2458eb44"
  },
  {
    "id": 13,
    "name": "\u0625\u0630\u0627\u0639\u0629 \u0627\u0644\u0642\u0631\u0627\u0646 \u0627\u0644\u0643\u0631\u064a\u0645",
    "logo": "",
    "stream": "https://live.kwikmotion.com/ksaquranradiolive/ksaquranradiovision/playlist_dvr.m3u8?hdnts=exp=1776680986~acl=/ksaquranradiolive/ksaquranradiovision/*~hmac=d075e01dc579eec95081b1125c5439f552dfac9ae9810edbf0eaf2538e0a4323"
  },
  {
    "id": 14,
    "name": "\u0625\u0630\u0627\u0639\u0629 \u0646\u062f\u0627\u0621 \u0627\u0644\u0627\u0633\u0644\u0627\u0645",
    "logo": "",
    "stream": "https://live.kwikmotion.com/ksanedaradiolive/ksanedaradiovision/playlist_dvr.m3u8?hdnts=exp=1776680987~acl=/ksanedaradiolive/ksanedaradiovision/*~hmac=f53d9e159ce93032cd0f04ecbb14435be7aaaeb31301927b8018ac4c818f0a89"
  },
  {
    "id": 18,
    "name": "\u0625\u0630\u0627\u0639\u0629 \u062e\u0632\u0627\u0645\u0649",
    "logo": "",
    "stream": "https://live.kwikmotion.com/khuzamaradiolive/khuzama_source/playlist.m3u8?hdnts=exp=1776680988~acl=/khuzamaradiolive/khuzama_source/*~hmac=c2aa550bbd47034881b4100f427e380f09d4d5664f9ab1497902571afed6c6c5"
  },
  {
    "id": 11,
    "name": "\u0631\u0627\u062f\u064a\u0648 \u0627\u0644\u0633\u0639\u0648\u062f\u064a\u0629",
    "logo": "",
    "stream": "https://live.kwikmotion.com/ksasaudiaradiolive/ksasaudiaradiovision/playlist_dvr.m3u8?hdnts=exp=1776680990~acl=/ksasaudiaradiolive/ksasaudiaradiovision/*~hmac=7b66634c2cf4c3c59c84334879d039f44df4b1e6f1a936ff0f3872b57e0e68c2"
  }
]