[
  {
    "id": 2,
    "name": "\u0642\u0646\u0627\u0629 \u0627\u0644\u0633\u0639\u0648\u062f\u064a\u0629 \u2013 \u0627\u0644\u0628\u062b \u0627\u0644\u0645\u0628\u0627\u0634\u0631",
    "logo": "",
    "stream": "https://live.kwikmotion.com/ksa1live/ksa1.smil/playlist_dvr.m3u8?hdnts=exp=1772857146~acl=/ksa1live/ksa1.smil/*~hmac=db1a788bf7bc0416d2fbe5a5e57044f3d5aac20bb8ed83f1d387d3e95a3d124f"
  },
  {
    "id": 1,
    "name": "\u0642\u0646\u0627\u0629 SBC \u2013 \u0627\u0644\u0628\u062b \u0627\u0644\u0645\u0628\u0627\u0634\u0631",
    "logo": "",
    "stream": "https://live.kwikmotion.com/sbclive/sbc.smil/playlist_dvr.m3u8?hdnts=exp=1772857147~acl=/sbclive/sbc.smil/*~hmac=c2a8b32a26564ccbff6aa45a1550a6b5f4e9cd75b7099dba39506968f54d3e0b"
  },
  {
    "id": 4,
    "name": "\u0642\u0646\u0627\u0629 \u0627\u0644\u0625\u062e\u0628\u0627\u0631\u064a\u0629 \u2013 \u0627\u0644\u0628\u062b \u0627\u0644\u0645\u0628\u0627\u0634\u0631",
    "logo": "",
    "stream": "https://live.kwikmotion.com/ikhbariyalive/ikhbariya.smil/playlist_dvr.m3u8?hdnts=exp=1772857149~acl=/ikhbariyalive/ikhbariya.smil/*~hmac=8428ab785596b7b7a8e00865cbd7a3333b470b3c7c4f800e8a0ed89286dbb195"
  },
  {
    "id": 17,
    "name": "\u0627\u0644\u0633\u0639\u0648\u062f\u064a\u0629 \u0627\u0644\u0622\u0646",
    "logo": "",
    "stream": "https://live.kwikmotion.com/ksasports4live/ksasports4.smil/playlist_dvr.m3u8?hdnts=exp=1772857150~acl=/ksasports4live/ksasports4.smil/*~hmac=c12f29c4b40c6e08e570cdeda3e17d910a1d558e1fb2ade3f6af9167420f287a"
  },
  {
    "id": 3,
    "name": "\u0642\u0646\u0627\u0629 \u0630\u0643\u0631\u064a\u0627\u062a \u2013 \u0627\u0644\u0628\u062b \u0627\u0644\u0645\u0628\u0627\u0634\u0631",
    "logo": "",
    "stream": "https://live.kwikmotion.com/zikrayatlive/zikrayat.smil/playlist_dvr.m3u8?hdnts=exp=1772857151~acl=/zikrayatlive/zikrayat.smil/*~hmac=aebbdc550b0c44b6931b9b585f8ff1fed5e798d7fb2873d05040474a06b340ad"
  },
  {
    "id": 7,
    "name": "\u0642\u0646\u0627\u0629 \u0627\u0644\u0642\u0631\u0622\u0646 \u0627\u0644\u0643\u0631\u064a\u0645 \u2013 \u0627\u0644\u0628\u062b \u0627\u0644\u0645\u0628\u0627\u0634\u0631",
    "logo": "",
    "stream": "https://live.kwikmotion.com/ksaquranlive/ksaquran.smil/playlist_dvr.m3u8?hdnts=exp=1772857151~acl=/ksaquranlive/ksaquran.smil/*~hmac=c395370f6568e56d25610f45d357284742ba6a2e817471b328cc5fabfd8a24bb"
  },
  {
    "id": 6,
    "name": "\u0642\u0646\u0627\u0629 \u0627\u0644\u0633\u0646\u0629 \u0627\u0644\u0646\u0628\u0648\u064a\u0629 \u2013 \u0627\u0644\u0628\u062b \u0627\u0644\u0645\u0628\u0627\u0634\u0631",
    "logo": "",
    "stream": "https://live.kwikmotion.com/ksasunnalive/ksasunna.smil/playlist_dvr.m3u8?hdnts=exp=1772857154~acl=/ksasunnalive/ksasunna.smil/*~hmac=7dd236ffa232b3de58efc2b0ac67549f83fbdf0db25ac509d5feaeb9bb276d99"
  },
  {
    "id": 9,
    "name": "\u0642\u0646\u0627\u0629 \u0627\u0644\u0631\u064a\u0627\u0636\u064a\u0629 1",
    "logo": "",
    "stream": "https://live.kwikmotion.com/ksasports1live/ksasports1.smil/playlist_dvr.m3u8?hdnts=exp=1772857155~acl=/ksasports1live/ksasports1.smil/*~hmac=b76aa4866b5c4f31301fd274ab9690c2e8af4f432b70949b7e71f887170307a0"
  },
  {
    "id": 10,
    "name": "\u0642\u0646\u0627\u0629 \u0627\u0644\u0631\u064a\u0627\u0636\u064a\u0629 2",
    "logo": "",
    "stream": "https://live.kwikmotion.com/ksasports2live/ksasports2.smil/playlist_dvr.m3u8?hdnts=exp=1772857156~acl=/ksasports2live/ksasports2.smil/*~hmac=449400a1300450b4e19fb0b8f0e2c1ca6c79d91c3c3f329d015dba0f06fc669d"
  },
  {
    "id": 16,
    "name": "\u0642\u0646\u0627\u0629 \u0627\u0644\u0631\u064a\u0627\u0636\u064a\u0629 3",
    "logo": "",
    "stream": "https://live.kwikmotion.com/ksasports3live/ksasports3.smil/playlist_dvr.m3u8?hdnts=exp=1772857158~acl=/ksasports3live/ksasports3.smil/*~hmac=d20ad95246d147ece254eb7117f67f5ea2d53560c03f20628d381da33f5f34c6"
  },
  {
    "id": 12,
    "name": "\u0625\u0630\u0627\u0639\u0629 \u0627\u0644\u0631\u064a\u0627\u0636",
    "logo": "",
    "stream": "https://live.kwikmotion.com/ksariyadhradiolive/ksariyadhradiovision/playlist_dvr.m3u8?hdnts=exp=1772857159~acl=/ksariyadhradiolive/ksariyadhradiovision/*~hmac=41a7214a6d6a2638c251df13c44cbb1cd43ac576a6e40da8ff7ac9898ea28693"
  },
  {
    "id": 15,
    "name": "\u0625\u0630\u0627\u0639\u0629 \u062c\u062f\u0629",
    "logo": "",
    "stream": "https://live.kwikmotion.com/ksajeddahradiolive/ksajeddahradiovision/playlist_dvr.m3u8?hdnts=exp=1772857160~acl=/ksajeddahradiolive/ksajeddahradiovision/*~hmac=a2d0421509764bd524e4afc4ce40893424023506f15bfef50a6aadcaced0a8da"
  },
  {
    "id": 13,
    "name": "\u0625\u0630\u0627\u0639\u0629 \u0627\u0644\u0642\u0631\u0627\u0646 \u0627\u0644\u0643\u0631\u064a\u0645",
    "logo": "",
    "stream": "https://live.kwikmotion.com/ksaquranradiolive/ksaquranradiovision/playlist_dvr.m3u8?hdnts=exp=1772857161~acl=/ksaquranradiolive/ksaquranradiovision/*~hmac=9d6104721342dc89804d399b5d40e4f7fbfa18ae3384a3208c0a8b574d861c43"
  },
  {
    "id": 14,
    "name": "\u0625\u0630\u0627\u0639\u0629 \u0646\u062f\u0627\u0621 \u0627\u0644\u0627\u0633\u0644\u0627\u0645",
    "logo": "",
    "stream": "https://live.kwikmotion.com/ksanedaradiolive/ksanedaradiovision/playlist_dvr.m3u8?hdnts=exp=1772857163~acl=/ksanedaradiolive/ksanedaradiovision/*~hmac=fe01f70884f8a867031c9e084dd3025f2701734b882b40f007d57998d8a23c44"
  },
  {
    "id": 18,
    "name": "\u0625\u0630\u0627\u0639\u0629 \u062e\u0632\u0627\u0645\u0649",
    "logo": "",
    "stream": "https://live.kwikmotion.com/khuzamaradiolive/khuzama_source/playlist.m3u8?hdnts=exp=1772857164~acl=/khuzamaradiolive/khuzama_source/*~hmac=a9be61b98b0df2cb2d11c6b725154b250d771d75bc91b0e371e855cae83ae80c"
  },
  {
    "id": 11,
    "name": "\u0631\u0627\u062f\u064a\u0648 \u0627\u0644\u0633\u0639\u0648\u062f\u064a\u0629",
    "logo": "",
    "stream": "https://live.kwikmotion.com/ksasaudiaradiolive/ksasaudiaradiovision/playlist_dvr.m3u8?hdnts=exp=1772857165~acl=/ksasaudiaradiolive/ksasaudiaradiovision/*~hmac=67407c56330b706c1ecb6ee061d4177938e1064166688717341315a137b50cd2"
  }
]